setup.py
eucaops/__init__.py
eucaops/asops.py
eucaops/cfnops.py
eucaops/cwops.py
eucaops/ec2ops.py
eucaops/elbops.py
eucaops/iamops.py
eucaops/s3ops.py
eucaops/stsops.py
eucaweb/__init__.py
eucaweb/euwebaccount.py
eucaweb/euwebglobals.py
eucaweb/euwebgroup.py
eucaweb/euwebuser.py
eucaweb/example_get_creds_via_webui.py
eucaweb/webtestcase.py
eutester/__init__.py
eutester/euconfig.py
eutester/euinstance.py
eutester/eulogger.py
eutester/eupopulator.py
eutester/euproperties.py
eutester/euservice.py
eutester/eusnapshot.py
eutester/eutestcase.py
eutester/euvolume.py
eutester/euzone.py
eutester/machine.py
eutester/process_manager.py
eutester/repoutils.py
eutester/sshconnection.py
eutester/taggedresource.py
eutester/testtimer.py
eutester/timer.py
eutester/windows_instance.py
eutester/winrm_connection.py
eutester/xmlrunner.py
eutester.egg-info/PKG-INFO
eutester.egg-info/SOURCES.txt
eutester.egg-info/dependency_links.txt
eutester.egg-info/requires.txt
eutester.egg-info/top_level.txt
testcases/__init__.py
testcases/cloud_admin/__init__.py
testcases/cloud_admin/change_property.py
testcases/cloud_admin/change_vlan_range.py
testcases/cloud_admin/clusterbasics.py
testcases/cloud_admin/create_resources.py
testcases/cloud_admin/create_user.py
testcases/cloud_admin/get_cred.py
testcases/cloud_admin/get_debug.py
testcases/cloud_admin/ha.py
testcases/cloud_admin/install_euca.py
testcases/cloud_admin/install_imaging_service.py
testcases/cloud_admin/install_loadbalancer.py
testcases/cloud_admin/instance_restore.py
testcases/cloud_admin/lvm_snapshot_utility.py
testcases/cloud_admin/migration.py
testcases/cloud_admin/net_tests.py
testcases/cloud_admin/reporting.py
testcases/cloud_admin/restart_nc.py
testcases/cloud_admin/run_commands.py
testcases/cloud_admin/run_sos_report.py
testcases/cloud_admin/services_up_test.py
testcases/cloud_admin/sts_ui.py
testcases/cloud_admin/testcase_template.py
testcases/cloud_admin/upgrade_euca.py
testcases/cloud_user/__init__.py
testcases/cloud_user/testcase_template.py
testcases/cloud_user/ebs/__init__.py
testcases/cloud_user/ebs/block_dev_map_tests.py
testcases/cloud_user/ebs/check_vol_on_stop_start.py
