Metadata-Version: 1.1
Name: eutester
Version: 0.0.10
Summary: Test Framework for AWS compatible clouds
Home-page: http://open.eucalyptus.com
Author: Victor Iglesias
Author-email: vic.iglesias@eucalyptus.com
License: BSD (Simplified)
Platform: Posix; MacOS X; Windows
Classifier: Development Status :: 3 - Alpha
Classifier: Intended Audience :: System Administrators
Classifier: License :: OSI Approved :: BSD License
Classifier: Operating System :: OS Independent
Classifier: Topic :: System :: Systems Administration
